fourier_classification/__init__.py
fourier_classification/fourier.py
fourier_classification/models.py
fourier_classification/operations.py
fourier_classification/signals.py
fourier_classification/utils.py
fourier_classification/visualization.py
fourier_classification-1.0.0.dist-info/METADATA
fourier_classification-1.0.0.dist-info/WHEEL
fourier_classification-1.0.0.dist-info/top_level.txt
fourier_classification-1.0.0.dist-info/RECORD
