Metadata-Version: 2.4
Name: Fourier_Classification
Version: 1.0.0
Summary: A package for classifying 1D signals using Fourier Series and Machine Learning
Home-page: https://github.com/abbass12/FourierSeriesClassification
Author: Abbass Srour
Author-email: abbasss@umich.edu
Keywords: fourier,signal processing,machine learning,classification
Requires-Python: >=3.6
Requires-Dist: numpy>=1.19.0
Requires-Dist: pandas>=1.0.0
Requires-Dist: plotly>=4.14.0
Requires-Dist: tensorflow>=2.4.0
Requires-Dist: matplotlib>=3.3.0
Requires-Dist: scikit-learn>=0.24.0
Dynamic: author
Dynamic: author-email
Dynamic: description
Dynamic: description-content-type
Dynamic: home-page
Dynamic: keywords
Dynamic: requires-dist
Dynamic: requires-python
Dynamic: summary
